Metadata-Version: 2.1
Name: log4python
Version: 1.0.10
Summary: log for python like log4j2
Home-page: https://github.com/starwithmoon/log4p
Author: li_jia_yue
Author-email: 59727816@qq.com
License: BSD
Keywords: log for python
Classifier: Development Status :: 3 - Alpha
Classifier: Framework :: Django
Classifier: Intended Audience :: Developers
Classifier: License :: OSI Approved :: BSD License
Classifier: Natural Language :: English
Classifier: Programming Language :: Python :: 2.6
Classifier: Programming Language :: Python :: 2.7
Classifier: Programming Language :: Python :: 3.3
Classifier: Programming Language :: Python :: 3.4
Classifier: Programming Language :: Python :: 3.7
